prime_iroh-0.3.1.dist-info/METADATA
prime_iroh-0.3.1.dist-info/WHEEL
prime_iroh-0.3.1.dist-info/licenses/LICENSE
prime_iroh/__init__.py
prime_iroh/_prime_iroh.cpython-39-x86_64-linux-gnu.so
prime_iroh/_prime_iroh.pyi
prime_iroh-0.3.1.dist-info/RECORD
