Metadata-Version: 2.4
Name: prime_iroh
Version: 0.3.1
Classifier: Programming Language :: Rust
Classifier: Programming Language :: Python
Classifier: License :: OSI Approved :: MIT License
Classifier: Operating System :: POSIX :: Linux
License-File: LICENSE
Summary: Asynchronous P2P communication backend for decentralized pipeline parallelism, built on top of Iroh
Author-email: Mika Senghaas <mika@primeintellect.ai>
License: MIT
Requires-Python: >=3.9
Project-URL: Documentation, https://github.com/PrimeIntellect-ai/prime-iroh
Project-URL: Repository, https://github.com/PrimeIntellect-ai/prime-iroh
Project-URL: Issues, https://github.com/PrimeIntellect-ai/prime-iroh/issues
